modio/__init__.py
modio/client.py
modio/entities.py
modio/enums.py
modio/errors.py
modio/game.py
modio/mixins.py
modio/mod.py
modio/objects.py
modio/utils.py
mod.io-0.6.0.dist-info/LICENSE
mod.io-0.6.0.dist-info/METADATA
mod.io-0.6.0.dist-info/WHEEL
mod.io-0.6.0.dist-info/top_level.txt
mod.io-0.6.0.dist-info/RECORD
