Metadata-Version: 2.1
Name: mod.io
Version: 0.6.0
Summary: mod.io python wrapper
Home-page: https://github.com/ClementJ18/mod.io
Author: Clement Julia
Author-email: clement.julia13@gmail.com
License-File: LICENSE
Requires-Dist: aiohttp (==3.8.1)
Requires-Dist: requests (==2.31.0)
Requires-Dist: typing-extensions (==4.3.0)
